{
	"name": "df_DimProduct_dedup_v1",
	"properties": {
		"type": "MappingDataFlow",
		"typeProperties": {
			"sources": [
				{
					"dataset": {
						"referenceName": "ds_appdb_product",
						"type": "DatasetReference"
					},
					"name": "sourceProduct"
				},
				{
					"dataset": {
						"referenceName": "ds_appdb_ProductModel",
						"type": "DatasetReference"
					},
					"name": "sourceProductModel"
				},
				{
					"dataset": {
						"referenceName": "ds_appdb_ProductCategory",
						"type": "DatasetReference"
					},
					"name": "sourceProductCategory"
				},
				{
					"dataset": {
						"referenceName": "ds_synapse_DimProduct",
						"type": "DatasetReference"
					},
					"name": "LatestProducts"
				}
			],
			"sinks": [
				{
					"dataset": {
						"referenceName": "ds_synapse_DimProduct",
						"type": "DatasetReference"
					},
					"name": "sinkDimProduct"
				}
			],
			"transformations": [
				{
					"name": "joinProductAndProductModel"
				},
				{
					"name": "joinProductAndProductCategory"
				},
				{
					"name": "IfProductNotexists"
				}
			],
			"scriptLines": [
				"source(output(",
				"          ProductID as integer,",
				"          Name as string,",
				"          ProductNumber as string,",
				"          Color as string,",
				"          StandardCost as decimal(19,4),",
				"          ListPrice as decimal(19,4),",
				"          Size as string,",
				"          Weight as decimal(8,2),",
				"          ProductCategoryID as integer,",
				"          ProductModelID as integer,",
				"          SellStartDate as timestamp,",
				"          SellEndDate as timestamp,",
				"          DiscontinuedDate as timestamp,",
				"          ThumbNailPhoto as binary,",
				"          ThumbnailPhotoFileName as string,",
				"          rowguid as string,",
				"          ModifiedDate as timestamp",
				"     ),",
				"     allowSchemaDrift: true,",
				"     validateSchema: false,",
				"     isolationLevel: 'READ_UNCOMMITTED',",
				"     format: 'table') ~> sourceProduct",
				"source(output(",
				"          ProductModelID as integer,",
				"          Name as string,",
				"          CatalogDescription as string,",
				"          rowguid as string,",
				"          ModifiedDate as timestamp",
				"     ),",
				"     allowSchemaDrift: true,",
				"     validateSchema: false,",
				"     isolationLevel: 'READ_UNCOMMITTED',",
				"     format: 'table') ~> sourceProductModel",
				"source(output(",
				"          ProductCategoryID as integer,",
				"          ParentProductCategoryID as integer,",
				"          Name as string,",
				"          rowguid as string,",
				"          ModifiedDate as timestamp",
				"     ),",
				"     allowSchemaDrift: true,",
				"     validateSchema: false,",
				"     isolationLevel: 'READ_UNCOMMITTED',",
				"     format: 'table') ~> sourceProductCategory",
				"source(output(",
				"          ProductID as integer,",
				"          ProductModelID as integer,",
				"          ProductcategoryID as integer,",
				"          ProductName as string,",
				"          ProductModelName as string,",
				"          ProductCategoryName as string",
				"     ),",
				"     allowSchemaDrift: true,",
				"     validateSchema: false,",
				"     isolationLevel: 'READ_UNCOMMITTED',",
				"     format: 'table',",
				"     staged: true) ~> LatestProducts",
				"IfProductNotexists, sourceProductModel join(sourceProduct@ProductModelID == sourceProductModel@ProductModelID,",
				"     joinType:'left',",
				"     matchType:'exact',",
				"     ignoreSpaces: false,",
				"     broadcast: 'auto')~> joinProductAndProductModel",
				"joinProductAndProductModel, sourceProductCategory join(sourceProduct@ProductCategoryID == sourceProductCategory@ProductCategoryID,",
				"     joinType:'left',",
				"     matchType:'exact',",
				"     ignoreSpaces: false,",
				"     broadcast: 'auto')~> joinProductAndProductCategory",
				"sourceProduct, LatestProducts exists(sourceProduct@ProductID == LatestProducts@ProductID,",
				"     negate:true,",
				"     broadcast: 'auto')~> IfProductNotexists",
				"joinProductAndProductCategory sink(allowSchemaDrift: true,",
				"     validateSchema: false,",
				"     input(",
				"          ProductID as integer,",
				"          ProductModelID as integer,",
				"          ProductcategoryID as integer,",
				"          ProductName as string,",
				"          ProductModelName as string,",
				"          ProductCategoryName as string",
				"     ),",
				"     deletable:false,",
				"     insertable:true,",
				"     updateable:false,",
				"     upsertable:false,",
				"     format: 'table',",
				"     staged: true,",
				"     allowCopyCommand: true,",
				"     skipDuplicateMapInputs: true,",
				"     skipDuplicateMapOutputs: true,",
				"     errorHandlingOption: 'stopOnFirstError',",
				"     mapColumn(",
				"          ProductID,",
				"          ProductModelID = sourceProduct@ProductModelID,",
				"          ProductcategoryID = sourceProduct@ProductCategoryID,",
				"          ProductName = sourceProduct@Name,",
				"          ProductModelName = sourceProductModel@Name,",
				"          ProductCategoryName = sourceProductCategory@Name",
				"     )) ~> sinkDimProduct"
			]
		}
	}
}